mortar_mixins/__init__.py
mortar_mixins/common.py
mortar_mixins/temporal.py
mortar_mixins/testing.py
mortar_mixins-3.0.0.dist-info/LICENSE.txt
mortar_mixins-3.0.0.dist-info/METADATA
mortar_mixins-3.0.0.dist-info/WHEEL
mortar_mixins-3.0.0.dist-info/top_level.txt
mortar_mixins-3.0.0.dist-info/RECORD
