Metadata-Version: 2.1
Name: mortar-mixins
Version: 3.0.0
Summary: SQLAlchemy mixins for use with Postgres.
Home-page: https://github.com/Mortar/mortar_mixins
Author: Chris Withers
Author-email: chris@withers.org
License: MIT
Platform: UNKNOWN
Classifier: Development Status :: 5 - Production/Stable
Classifier: Intended Audience :: Developers
Classifier: License :: OSI Approved :: MIT License
Classifier: Programming Language :: Python :: 3
Requires-Python: >=3.7
License-File: LICENSE.txt
Requires-Dist: SQLAlchemy
Requires-Dist: psycopg2
Provides-Extra: build
Requires-Dist: setuptools-git ; extra == 'build'
Requires-Dist: wheel ; extra == 'build'
Requires-Dist: twine ; extra == 'build'
Provides-Extra: test
Requires-Dist: pytest ; extra == 'test'
Requires-Dist: pytest-cov ; extra == 'test'
Requires-Dist: testfixtures ; extra == 'test'
